geniuspy/__init__.py
geniuspy-0.0.2.dist-info/LICENSE
geniuspy-0.0.2.dist-info/METADATA
geniuspy-0.0.2.dist-info/WHEEL
geniuspy-0.0.2.dist-info/top_level.txt
geniuspy-0.0.2.dist-info/RECORD
