Metadata-Version: 2.1
Name: geniuspy
Version: 0.0.2
Summary: A Python wrapper around the Genius API
Home-page: https://github.com/lletfrix/geniuspy
Author: Rafael Sánchez Sánchez
Author-email: lletfrix@gmail.com
License: UNKNOWN
Platform: UNKNOWN
Classifier: Programming Language :: Python :: 3
Classifier: License :: OSI Approved :: MIT License
Classifier: Operating System :: OS Independent
Requires-Python: >=3.6
